comp_req/__init__.py
comp_req/chat_completion_request.py
chatcompletionreq-0.1.0.dist-info/METADATA
chatcompletionreq-0.1.0.dist-info/WHEEL
chatcompletionreq-0.1.0.dist-info/top_level.txt
chatcompletionreq-0.1.0.dist-info/RECORD
