Metadata-Version: 2.4
Name: chatcompletionreq
Version: 0.1.0
Summary: A simple library to wrap chat completion requests
Home-page: https://github.com/WiiLife/chatcompletionreq
Author: William Ambrosetti
Requires-Python: >=3.10
Requires-Dist: requests
Dynamic: author
Dynamic: description-content-type
Dynamic: home-page
Dynamic: requires-dist
Dynamic: requires-python
Dynamic: summary
